cfut/__init__.py
cfut/condor.py
cfut/remote.py
cfut/slurm.py
cfut/util.py
clusterfutures-0.5.dist-info/METADATA
clusterfutures-0.5.dist-info/WHEEL
clusterfutures-0.5.dist-info/top_level.txt
clusterfutures-0.5.dist-info/RECORD
