Metadata-Version: 2.1
Name: clusterfutures
Version: 0.5
Summary: futures for remote execution on clusters
Home-page: https://github.com/sampsyo/clusterfutures
Author: Adrian Sampson
Author-email: asampson@cs.washington.edu
License: MIT
Platform: ALL
Classifier: Intended Audience :: Developers
Classifier: Intended Audience :: Science/Research
Requires-Python: >=3.7
Requires-Dist: cloudpickle
Provides-Extra: test
Requires-Dist: pytest ; extra == 'test'
Requires-Dist: testpath (>=0.5) ; extra == 'test'
